file2db/__init__.py
file2db/commands.py
file2db/db.py
file2db/parser.py
file2db-0.8.0.data/scripts/file2db
file2db-0.8.0.dist-info/DESCRIPTION.rst
file2db-0.8.0.dist-info/METADATA
file2db-0.8.0.dist-info/RECORD
file2db-0.8.0.dist-info/WHEEL
file2db-0.8.0.dist-info/metadata.json
file2db-0.8.0.dist-info/top_level.txt
