Metadata-Version: 2.0
Name: file2db
Version: 0.8.0
Summary: Simple file to database manipulation
Home-page: https://github.com/moosejaw/file2db
Author: Matthew Vincent
Author-email: mattjvincent@gmail.com
License: GPLv3
Keywords: file2db
Platform: UNKNOWN
Classifier: Development Status :: 2 - Pre-Alpha
Classifier: Intended Audience :: Developers
Classifier: License :: OSI Approved :: GNU General Public License v3 (GPLv3)
Classifier: Natural Language :: English
Classifier: Programming Language :: Python :: 2
Classifier: Programming Language :: Python :: 2.6
Classifier: Programming Language :: Python :: 2.7
Classifier: Programming Language :: Python :: 3
Classifier: Programming Language :: Python :: 3.3
Classifier: Programming Language :: Python :: 3.4
